tap_facebook_posts
