Metadata-Version: 1.2
Name: tap-facebook-posts
Version: 0.0.4
Summary: Singer.io tap for extracting posts data from the Facebook Graph API
Home-page: https://github.com/rowanv
Author: rowanv
Author-email: UNKNOWN
License: Apache 2.0
Platform: UNKNOWN
Classifier: Programming Language :: Python :: 3 :: Only
Requires-Python: >=3
